lightecc/__init__.py
lightecc/commons/__init__.py
lightecc/commons/binary_operations.py
lightecc/commons/logger.py
lightecc/curves/__init__.py
lightecc/curves/edwards.py
lightecc/curves/inventory.py
lightecc/curves/koblitz.py
lightecc/curves/weierstrass.py
lightecc/forms/__init__.py
lightecc/forms/edwards.py
lightecc/forms/koblitz.py
lightecc/forms/weierstrass.py
lightecc/interfaces/__init__.py
lightecc/interfaces/elliptic_curve.py
lightecc/interfaces/form.py
lightecc-0.0.4.data/data/README.md
lightecc-0.0.4.data/data/requirements.txt
lightecc-0.0.4.dist-info/LICENSE
lightecc-0.0.4.dist-info/METADATA
lightecc-0.0.4.dist-info/WHEEL
lightecc-0.0.4.dist-info/top_level.txt
lightecc-0.0.4.dist-info/RECORD
