Metadata-Version: 2.1
Name: lightecc
Version: 0.0.4
Summary: A Lightweight Elliptic Curve Cryptography Arithmetic Library for Python with Support for Prime and Binary Fields
Home-page: https://github.com/serengil/LightECC
Author: Sefik Ilkin Serengil
Author-email: serengil@gmail.com
License: UNKNOWN
Platform: UNKNOWN
Classifier: Programming Language :: Python :: 3
Classifier: License :: OSI Approved :: MIT License
Classifier: Operating System :: OS Independent
Requires-Python: >=3.5.5
License-File: LICENSE
